kozumikku/__init__.py
kozumikku/client.py
kozumikku/errors.py
kozumikku/http.py
kozumikku.py-1.0.0a0.dist-info/METADATA
kozumikku.py-1.0.0a0.dist-info/WHEEL
kozumikku.py-1.0.0a0.dist-info/top_level.txt
kozumikku.py-1.0.0a0.dist-info/RECORD
