Metadata-Version: 2.1
Name: kozumikku.py
Version: 1.0.0a0
Summary: A robust asynchronous framework for interacting with the Kozumikku API
Home-page: UNKNOWN
Author: justanotherbyte
License: MIT
Platform: UNKNOWN
Classifier: Development Status :: 5 - Production/Stable
Classifier: License :: OSI Approved :: MIT License
Classifier: Intended Audience :: Developers
Classifier: Natural Language :: English
Classifier: Operating System :: OS Independent
Classifier: Programming Language :: Python :: 3.8
Classifier: Programming Language :: Python :: 3.9
Classifier: Topic :: Internet
Classifier: Topic :: Software Development :: Libraries
Classifier: Topic :: Software Development :: Libraries :: Python Modules
Classifier: Topic :: Utilities
Classifier: Typing :: Typed
Requires-Dist: aiohttp (>=3.8.1)
Provides-Extra: speedups
Requires-Dist: aiohttp[speedups] ; extra == 'speedups'
